request_tracker/__init__.py
request_tracker/tracker.py
request_tracker-0.2.3.dist-info/METADATA
request_tracker-0.2.3.dist-info/WHEEL
request_tracker-0.2.3.dist-info/entry_points.txt
request_tracker-0.2.3.dist-info/top_level.txt
request_tracker-0.2.3.dist-info/RECORD
