Metadata-Version: 2.1
Name: request_tracker
Version: 0.2.3
Summary: A package for tracking requests, code coverage, and data changes.
Home-page: https://github.com/vishalksimplify/request_tracker
Author: vishal kumar
Author-email: vishal.k@simplify3x.com
Classifier: Development Status :: 3 - Alpha
Classifier: Intended Audience :: Developers
Classifier: License :: OSI Approved :: MIT License
Classifier: Programming Language :: Python :: 3
Classifier: Programming Language :: Python :: 3.7
Classifier: Programming Language :: Python :: 3.8
Classifier: Programming Language :: Python :: 3.9
Classifier: Programming Language :: Python :: 3.10
Requires-Dist: Flask
Requires-Dist: SQLAlchemy
Requires-Dist: psycopg2-binary
